docker/sopa/Dockerfile
sopa/__init__.py
sopa/_logging.py
sopa/_settings.py
sopa/constants.py
sopa/main.py
sopa/aggregation/__init__.py
sopa/aggregation/aggregation.py
sopa/aggregation/bins.py
sopa/aggregation/channels.py
sopa/aggregation/overlay.py
sopa/aggregation/transcripts.py
sopa/cli/annotate.py
sopa/cli/app.py
sopa/cli/explorer.py
sopa/cli/patchify.py
sopa/cli/resolve.py
sopa/cli/segmentation.py
sopa/cli/utils.py
sopa/io/__init__.py
sopa/io/standardize.py
sopa/io/explorer/__init__.py
sopa/io/explorer/_constants.py
sopa/io/explorer/converter.py
sopa/io/explorer/images.py
sopa/io/explorer/points.py
sopa/io/explorer/shapes.py
sopa/io/explorer/table.py
sopa/io/explorer/utils.py
sopa/io/reader/__init__.py
sopa/io/reader/_wsi_reader.py
sopa/io/reader/_wsi_store.py
sopa/io/reader/cosmx.py
sopa/io/reader/generic.py
sopa/io/reader/hyperion.py
sopa/io/reader/macsima.py
sopa/io/reader/merscope.py
sopa/io/reader/molecular_cartography.py
sopa/io/reader/phenocycler.py
sopa/io/reader/utils.py
sopa/io/reader/visium_hd.py
sopa/io/reader/wsi.py
sopa/io/reader/xenium.py
sopa/io/report/__init__.py
sopa/io/report/css.py
sopa/io/report/engine.py
sopa/io/report/generate.py
sopa/patches/__init__.py
sopa/patches/cluster.py
sopa/patches/factory.py
sopa/patches/infer.py
sopa/patches/loader.py
sopa/patches/patches.py
sopa/patches/transcripts.py
sopa/patches/models/__init__.py
sopa/patches/models/conch.py
sopa/patches/models/dinov2.py
sopa/patches/models/dummy.py
sopa/patches/models/histo_ssl.py
sopa/patches/models/hoptimus0.py
sopa/patches/models/resnet.py
sopa/segmentation/__init__.py
sopa/segmentation/_tissue.py
sopa/segmentation/resolve.py
sopa/segmentation/stainings.py
sopa/segmentation/methods/__init__.py
sopa/segmentation/methods/_baysor.py
sopa/segmentation/methods/_cellpose.py
sopa/segmentation/methods/_comseg.py
sopa/segmentation/methods/_custom.py
sopa/segmentation/methods/_dummy.py
sopa/segmentation/methods/_proseg.py
sopa/segmentation/methods/_stardist.py
sopa-2.1.11.dist-info/METADATA
sopa-2.1.11.dist-info/WHEEL
sopa-2.1.11.dist-info/entry_points.txt
sopa-2.1.11.dist-info/licenses/LICENSE
sopa-2.1.11.dist-info/RECORD
