Metadata-Version: 2.4
Name: sopa
Version: 2.1.11
Summary: Spatial-omics pipeline and analysis
Project-URL: Homepage, https://gustaveroussy.github.io/sopa
Project-URL: Repository, https://github.com/gustaveroussy/sopa
Project-URL: Documentation, https://gustaveroussy.github.io/sopa
Author-email: Quentin Blampey <quentin.blampey@gmail.com>
License-Expression: BSD-3-Clause
License-File: LICENSE
Classifier: License :: OSI Approved :: BSD License
Classifier: Operating System :: MacOS :: MacOS X
Classifier: Operating System :: Microsoft :: Windows
Classifier: Operating System :: POSIX :: Linux
Classifier: Programming Language :: Python :: 3
Classifier: Topic :: Scientific/Engineering
Requires-Python: >=3.10
Requires-Dist: anndata>=0.11.0
Requires-Dist: dask[distributed]>=2024.4.1
Requires-Dist: igraph>=0.11.0
Requires-Dist: pyarrow<22.0.0
Requires-Dist: scanpy>=1.10.4
Requires-Dist: spatialdata-io>=0.3.0
Requires-Dist: spatialdata-plot>=0.2.10
Requires-Dist: spatialdata>=0.5.0
Requires-Dist: typer>=0.9.0
Requires-Dist: zarr<3.0.0
Provides-Extra: baysor
Requires-Dist: loompy>=3.0.7; extra == 'baysor'
Requires-Dist: toml>=0.10.2; extra == 'baysor'
Provides-Extra: cellpose
Requires-Dist: cellpose>=3.0.5; extra == 'cellpose'
Requires-Dist: opencv-python>=4.8.0; extra == 'cellpose'
Requires-Dist: torch>=2.1.1; extra == 'cellpose'
Provides-Extra: stardist
Requires-Dist: stardist>=0.9.2; extra == 'stardist'
Requires-Dist: tensorflow>=2.18.0; extra == 'stardist'
Provides-Extra: wsi
Requires-Dist: tiffslide>=2.3.1; extra == 'wsi'
Requires-Dist: torch>=2.1.1; extra == 'wsi'
Requires-Dist: torchvision>=0.20.0; extra == 'wsi'
